LICENSE
p189client/.DS_Store
p189client/__init__.py
p189client/client.py
p189client/const.py
p189client/exception.py
p189client/py.typed
p189client-0.0.2.3.dist-info/LICENSE
p189client-0.0.2.3.dist-info/METADATA
p189client-0.0.2.3.dist-info/WHEEL
p189client-0.0.2.3.dist-info/RECORD
